bcitflex/__init__.py
bcitflex/account.py
bcitflex/alembic/README
bcitflex/alembic/alembic.ini
bcitflex/alembic/env.py
bcitflex/alembic/script.py.mako
bcitflex/alembic/utils.py
bcitflex/alembic/versions/09d662433ed7_add_course_table.py
bcitflex/alembic/versions/178719586e69_add_user_table.py
bcitflex/alembic/versions/1ffa8d44f772_add_cascade_delete.py
bcitflex/alembic/versions/317d5306c14e_alter_course_url_length.py
bcitflex/alembic/versions/6205b7a86c7f_add_offering_meeting_time.py
bcitflex/alembic/versions/6253c78c6b3a_add_program_table.py
bcitflex/alembic/versions/6f25f0a31d7d_add_user_preference_table.py
bcitflex/alembic/versions/7034009b08f2_add_surrogate_key_to_offering_table.py
bcitflex/alembic/versions/83135043932d_add_on_delete_cascade_to_offering_term_.py
bcitflex/alembic/versions/86cd0f1798a8_add_offering_table.py
bcitflex/alembic/versions/871389a90551_add_subject_is_active_field.py
bcitflex/alembic/versions/8a725632af56_add_unique_constraint_to_course.py
bcitflex/alembic/versions/8cfa744d65d4_alter_course_field_types.py
bcitflex/alembic/versions/96a6aafa05d6_add_meeting_table.py
bcitflex/alembic/versions/a69dfec6b6c5_add_subject_table.py
bcitflex/alembic/versions/b663bbcd0412_alter_offering_crn_to_string.py
bcitflex/alembic/versions/b746cd9b6b41_add_building_column_to_meeting.py
bcitflex/alembic/versions/c3592c25409c_add_term_table.py
bcitflex/alembic/versions/d0c807fc8328_unique_constraint_naming_convention.py
bcitflex/alembic/versions/db4d9a6c53f9_add_prerequisite_tables.py
bcitflex/alembic/versions/ee39506eab40_add_soft_delete.py
bcitflex/alembic/versions/f1ef91929e99_add_timestamp_fields.py
bcitflex/alembic/versions/f8ac7b4c05a9_add_soft_delete_rules.py
bcitflex/app_functions/__init__.py
bcitflex/app_functions/course_query.py
bcitflex/auth.py
bcitflex/course.py
bcitflex/db.py
bcitflex/ext/__init__.py
bcitflex/ext/database.py
bcitflex/model/__init__.py
bcitflex/model/base.py
bcitflex/model/course.py
bcitflex/model/meeting.py
bcitflex/model/offering.py
bcitflex-3.11.0.dist-info/LICENSE
bcitflex-3.11.0.dist-info/METADATA
bcitflex-3.11.0.dist-info/WHEEL
bcitflex-3.11.0.dist-info/RECORD
