Metadata-Version: 2.1
Name: bcitflex
Version: 3.11.0
Summary: Browse BCIT Flex course offerings.
License: MIT
Author: Jonathan Biemond
Author-email: jbiemond@my.bcit.ca
Requires-Python: >=3.10,<4.0
Classifier: License :: OSI Approved :: MIT License
Classifier: Programming Language :: Python :: 3
Classifier: Programming Language :: Python :: 3.10
Classifier: Programming Language :: Python :: 3.11
Classifier: Programming Language :: Python :: 3.12
Requires-Dist: alembic (>=1.11.1,<2.0.0)
Requires-Dist: flask (>=2.3.3,<3.0.0)
Requires-Dist: flask-sqlalchemy (>=3.0.5,<4.0.0)
Requires-Dist: psycopg2 (>=2.9.6,<3.0.0)
Requires-Dist: pyfunctional (>=1.4.3,<2.0.0)
Requires-Dist: pysimplegui (>=4.60.4,<5.0.0)
Requires-Dist: requests (>=2.31.0,<3.0.0)
Requires-Dist: selectolax (>=0.3.12,<0.4.0)
Requires-Dist: sqlalchemy (>=2.0.19,<3.0.0)
Requires-Dist: tabulate (>=0.8.10,<0.9.0)
